{
  "Country": {
    "id": "01",
    "name": "China",
    "Capital": "Beijing",
    "Divisions": [
      "01",
      "02",
      "03",
      "04"
    ],
    "Districts": [
      "01",
      "02",
      "03"
    ]
  },
  "Divisions": {
    "id": "01",
    "name": "Shengdong",
    "Districts": [
      "01",
      "02"
    ]
  },
  "Districts": {
    "id": "01",
    "name": "Dongcheng",
    "Subdistricts": [
      "01",
      "02"
    ],
    "Postcodes": [
      100000,
      610000,
      404000
    ]
  },
  "Subdistricts": {
    "id": "01",
    "name": "Dailang",
    "Postcodes": [
      736200,
      404000,
      100000
    ]
  }
}